frankford/__init__.py
frankford/_frankford.py
frankford/gpu_code.cu
frankford-0.1.dist-info/METADATA
frankford-0.1.dist-info/WHEEL
frankford-0.1.dist-info/licenses/LICENSE
frankford-0.1.dist-info/RECORD
