Metadata-Version: 2.3
Name: frankford
Version: 0.1
Summary: Use the CUDA system to fit multiple datasets simultaneously using the Levenberg–Marquardt algorithm
Project-URL: Homepage, https://github.com/ed-o-saurus/frankford
Project-URL: Issues, https://github.com/ed-o-saurus/frankford/issues
Project-URL: Documentation, https://frankford.readthedocs.io/
Author-email: Ed Behn <ed@behn.us>
License-File: LICENSE
Classifier: Development Status :: 4 - Beta
Classifier: Environment :: GPU :: NVIDIA CUDA :: 12
Classifier: Intended Audience :: Science/Research
Classifier: License :: OSI Approved :: GNU General Public License v3 (GPLv3)
Classifier: Operating System :: POSIX :: Linux
Classifier: Programming Language :: Python :: 3
Requires-Python: >=3.10
Requires-Dist: cffi>=1.16.0
Requires-Dist: numba>=0.58.1
Requires-Dist: numpy>=1.25.2
Requires-Dist: pynvjitlink-cu12>=0.3.0
